config.py
main.py
ai/__init__.py
ai/base_processor.py
ai/gpt4.py
ai/perplexity.py
camera/__init__.py
camera/camera_manager.py
core/__init__.py
core/app.py
ocr/__init__.py
ocr/ocr_processor.py
robbinghood_ai_trivia-0.1.0.dist-info/licenses/LICENSE
ui/__init__.py
ui/display.py
ui/renderer.py
robbinghood_ai_trivia-0.1.0.dist-info/METADATA
robbinghood_ai_trivia-0.1.0.dist-info/WHEEL
robbinghood_ai_trivia-0.1.0.dist-info/entry_points.txt
robbinghood_ai_trivia-0.1.0.dist-info/top_level.txt
robbinghood_ai_trivia-0.1.0.dist-info/RECORD
