Metadata-Version: 2.4
Name: robbinghood-ai-trivia
Version: 0.1.0
Summary: An AI trivia assistant that uses your camera and multiple AI models.
Author-email: Sathvik <vikvang01@gmail.com>
Project-URL: Homepage, https://github.com/vikvang/robbinghood
Project-URL: Bug Tracker, https://github.com/vikvang/robbinghood/issues
Classifier: Programming Language :: Python :: 3
Classifier: Programming Language :: Python :: 3.8
Classifier: Programming Language :: Python :: 3.9
Classifier: Programming Language :: Python :: 3.10
Classifier: Programming Language :: Python :: 3.11
Classifier: Programming Language :: Python :: 3.12
Classifier: License :: OSI Approved :: MIT License
Classifier: Operating System :: OS Independent
Classifier: Intended Audience :: Developers
Classifier: Topic :: Software Development :: Libraries
Classifier: Topic :: Multimedia :: Video :: Capture
Classifier: Topic :: Scientific/Engineering :: Artificial Intelligence
Requires-Python: >=3.8
License-File: LICENSE
Requires-Dist: opencv-python>=4.5.0
Requires-Dist: requests>=2.25.0
Requires-Dist: python-dotenv>=0.15.0
Requires-Dist: pynput
Requires-Dist: google-cloud-vision>=2.0.0
Requires-Dist: numpy>=1.19.0
Dynamic: license-file
Dynamic: requires-python
